aucome/__init__.py
aucome/__main__.py
aucome/analysis.py
aucome/check.py
aucome/compare.py
aucome/orthology.py
aucome/reconstruction.py
aucome/spontaneous.py
aucome/structural.py
aucome/utils.py
aucome/workflow.py
aucome-0.5.1.dist-info/DESCRIPTION.rst
aucome-0.5.1.dist-info/METADATA
aucome-0.5.1.dist-info/RECORD
aucome-0.5.1.dist-info/WHEEL
aucome-0.5.1.dist-info/entry_points.txt
aucome-0.5.1.dist-info/metadata.json
aucome-0.5.1.dist-info/top_level.txt
